{
  "_class": "text",
  "attributedString": {
    "_class": "attributedString",
    "attributes": [
      {
        "_class": "stringAttribute",
        "attributes": {
          "MSAttributedStringColorAttribute": {
            "_class": "color",
            "alpha": 1,
            "blue": 1,
            "green": 1,
            "red": 1
          },
          "MSAttributedStringFontAttribute": {
            "_class": "fontDescriptor",
            "attributes": {
              "name": "Avenir-Book",
              "size": 15
            }
          },
          "kerning": -0.24,
          "paragraphStyle": {
            "_class": "paragraphStyle",
            "alignment": 0,
            "allowsDefaultTighteningForTruncation": 0,
            "maximumLineHeight": 20,
            "minimumLineHeight": 20
          }
        },
        "length": 3,
        "location": 0
      }
    ],
    "string": "348"
  },
  "automaticallyDrawOnUnderlyingPath": false,
  "booleanOperation": 0,
  "clippingMaskMode": 0,
  "do_objectID": "FF858F8B-4D58-4F70-BFD0-AD30DF82E56F",
  "dontSynchroniseWithSymbol": false,
  "exportOptions": {
    "_class": "exportOptions",
    "do_objectID": "7A3C7C61-4EC5-4E1D-B94A-394C7E7E80E6",
    "exportFormats": [
    ],
    "includedLayerIds": [
    ],
    "layerOptions": 0,
    "shouldTrim": false
  },
  "frame": {
    "_class": "rect",
    "constrainProportions": false,
    "do_objectID": "B66D2F38-6713-4CC3-87B1-1FFE02CFFB98",
    "height": 20,
    "width": 25,
    "x": 293,
    "y": 4
  },
  "glyphBounds": "{{0, 4}, {24, 12}}",
  "hasClippingMask": false,
  "isFixedToViewport": false,
  "isFlippedHorizontal": false,
  "isFlippedVertical": false,
  "isLocked": false,
  "isVisible": true,
  "layerListExpandedType": 0,
  "lineSpacingBehaviour": 2,
  "name": "348",
  "nameIsFixed": false,
  "resizingConstraint": 9,
  "resizingType": 0,
  "rotation": 0,
  "sharedStyleID": "E116A09F-FE3F-4476-99C4-5A676FFCD8C0",
  "shouldBreakMaskChain": false,
  "style": {
    "_class": "style",
    "do_objectID": "23F66703-C3B7-4027-A411-BF5EE546885C",
    "endMarkerType": 0,
    "miterLimit": 10,
    "startMarkerType": 0,
    "textStyle": {
      "_class": "textStyle",
      "do_objectID": "D50743AD-CC42-476A-BAB6-87CA5FA56550",
      "encodedAttributes": {
        "MSAttributedStringColorAttribute": {
          "_class": "color",
          "alpha": 1,
          "blue": 1,
          "green": 1,
          "red": 1
        },
        "MSAttributedStringFontAttribute": {
          "_class": "fontDescriptor",
          "attributes": {
            "name": "Avenir-Book",
            "size": 15
          }
        },
        "kerning": -0.24,
        "paragraphStyle": {
          "_class": "paragraphStyle",
          "alignment": 0,
          "allowsDefaultTighteningForTruncation": 0,
          "maximumLineHeight": 20,
          "minimumLineHeight": 20
        }
      },
      "verticalAlignment": 0
    },
    "windingRule": 1
  },
  "textBehaviour": 0,
  "userInfo": {
    "com.invisionlabs.duplicate": {
      "type-duplicate": {
        "action": "article",
        "options": {
          "section": "travel",
          "type": "body"
        },
        "title": "Travel"
      }
    }
  }
}