{
  "_class": "sharedStyle",
  "do_objectID": "501978E7-BD40-4037-9D43-BB919ADB8378",
  "name": "Body/Semibold/Center/Black/13pt",
  "value": {
    "_class": "style",
    "endMarkerType": 0,
    "miterLimit": 10,
    "startMarkerType": 0,
    "textStyle": {
      "_class": "textStyle",
      "encodedAttributes": {
        "MSAttributedStringColorAttribute": {
          "_class": "color",
          "alpha": 1,
          "blue": 0,
          "green": 0,
          "red": 0
        },
        "MSAttributedStringFontAttribute": {
          "_class": "fontDescriptor",
          "attributes": {
            "name": "SFUIText-Medium",
            "size": 13
          }
        },
        "kerning": -0.3135294,
        "paragraphStyle": {
          "_class": "paragraphStyle",
          "alignment": 2,
          "allowsDefaultTighteningForTruncation": 0,
          "maximumLineHeight": 22,
          "minimumLineHeight": 22
        }
      },
      "verticalAlignment": 0
    },
    "windingRule": 1
  }
}