{
  "_class": "artboard",
  "backgroundColor": {
    "_class": "color",
    "alpha": 1,
    "blue": 1,
    "green": 1,
    "red": 1
  },
  "booleanOperation": -1,
  "clippingMaskMode": 0,
  "do_objectID": "58F4EE43-6EE5-4FC2-9F00-9CDDFCD73B39",
  "exportOptions": {
    "_class": "exportOptions",
    "exportFormats": [
      {
        "_class": "exportFormat",
        "absoluteSize": 0,
        "fileFormat": "jpg",
        "name": "",
        "namingScheme": 0,
        "scale": 3,
        "visibleScaleType": 0
      }
    ],
    "includedLayerIds": [
    ],
    "layerOptions": 0,
    "shouldTrim": false
  },
  "frame": {
    "_class": "rect",
    "constrainProportions": false,
    "height": 812,
    "width": 375,
    "x": 961,
    "y": 1750
  },
  "groupLayout": {
    "_class": "MSImmutableFreeformGroupLayout"
  },
  "hasBackgroundColor": false,
  "hasClickThrough": true,
  "hasClippingMask": false,
  "horizontalRulerData": {
    "_class": "rulerData",
    "base": 0,
    "guides": [
    ]
  },
  "includeBackgroundColorInExport": true,
  "includeInCloudUpload": true,
  "isFixedToViewport": false,
  "isFlippedHorizontal": false,
  "isFlippedVertical": false,
  "isFlowHome": false,
  "isLocked": false,
  "isVisible": true,
  "layerListExpandedType": 1,
  "layers": [
    {
      "class": "rectangle",
      "id": "08FF224E-706D-44BA-B414-07C56416A831"
    },
    {
      "class": "group",
      "id": "41E22DB4-E753-4DA5-AFA5-3172421F4C49"
    },
    {
      "class": "group",
      "id": "48AE8500-F07A-4D66-863E-ADBB6ADFF458"
    },
    {
      "class": "group",
      "id": "65212CD0-D653-4D42-8FE0-A0F02ECA95EC"
    },
    {
      "class": "symbolInstance",
      "id": "9FDE9349-2F76-4B98-B6E6-376C274DE717"
    },
    {
      "class": "symbolInstance",
      "id": "D389FABF-A44B-4A35-8E42-3F225B34579E"
    },
    {
      "class": "symbolInstance",
      "id": "A3E9D0B6-88F7-4CD4-8082-DF4A5B26281F"
    },
    {
      "class": "shapePath",
      "id": "5DA40DAE-3182-4093-8F94-EDF94E7C2058"
    },
    {
      "class": "shapePath",
      "id": "72B0CE4E-DF71-4378-BDB6-9F5BF21C4689"
    },
    {
      "class": "shapePath",
      "id": "326954FC-5282-42B4-B2D7-0B8C2E38F5C2"
    },
    {
      "class": "shapePath",
      "id": "7724E159-9CE9-41A1-89AA-BF4D112105EB"
    },
    {
      "class": "shapePath",
      "id": "D7AC375D-BC55-4301-98BA-03824DE3FA04"
    }
  ],
  "layout": {
    "_class": "layoutGrid",
    "columnWidth": 30,
    "drawHorizontal": false,
    "drawHorizontalLines": false,
    "drawVertical": true,
    "gutterHeight": 12,
    "gutterWidth": 5,
    "guttersOutside": false,
    "horizontalOffset": 15,
    "isEnabled": false,
    "numberOfColumns": 10,
    "rowHeightMultiplication": 5,
    "totalWidth": 345
  },
  "name": "23_Message List",
  "nameIsFixed": true,
  "presetDictionary": {
    "allowResizedMatching": 1,
    "height": 812,
    "name": "iPhone XS",
    "offersLandscapeVariant": 1,
    "width": 375
  },
  "resizesContent": false,
  "resizingConstraint": 63,
  "resizingType": 0,
  "rotation": 0,
  "shouldBreakMaskChain": true,
  "style": {
    "_class": "style",
    "endMarkerType": 0,
    "miterLimit": 10,
    "startMarkerType": 0,
    "windingRule": 1
  },
  "verticalRulerData": {
    "_class": "rulerData",
    "base": 0,
    "guides": [
    ]
  }
}