{
  "_class": "symbolInstance",
  "booleanOperation": -1,
  "clippingMaskMode": 0,
  "do_objectID": "27475CDD-0038-417D-BA3E-08EBB81CE65A",
  "exportOptions": {
    "_class": "exportOptions",
    "do_objectID": "4E5C0755-6108-43FE-A206-32075376BB29",
    "exportFormats": [
    ],
    "includedLayerIds": [
    ],
    "layerOptions": 0,
    "shouldTrim": false
  },
  "frame": {
    "_class": "rect",
    "constrainProportions": false,
    "do_objectID": "D3731F0C-0B09-4333-88A2-0ED9A58CAECA",
    "height": 28,
    "width": 28,
    "x": 15,
    "y": 52
  },
  "hasClippingMask": false,
  "horizontalSpacing": 0,
  "isFixedToViewport": false,
  "isFlippedHorizontal": false,
  "isFlippedVertical": false,
  "isLocked": false,
  "isVisible": true,
  "layerListExpandedType": 0,
  "name": "_Icons / Close Copy 3",
  "nameIsFixed": false,
  "overrideValues": [
    {
      "_class": "overrideValue",
      "do_objectID": "E850E894-CB0E-42B1-B97C-1A0AC4A752B8",
      "overrideName": "573EDD57-91D0-4BEA-B1F7-D8FD1876B723_layerStyle",
      "value": "307B1335-E31B-4FD6-871F-57B4DEE1CAE6"
    }
  ],
  "resizingConstraint": 63,
  "resizingType": 0,
  "rotation": 0,
  "scale": 1,
  "shouldBreakMaskChain": false,
  "style": {
    "_class": "style",
    "do_objectID": "66271197-553B-46A2-9A96-1FDBBA7D4226",
    "endMarkerType": 0,
    "miterLimit": 10,
    "startMarkerType": 0,
    "windingRule": 1
  },
  "symbolID": "3766177F-A4AE-48CF-9B52-95529D938026",
  "verticalSpacing": 0
}