{
  "_class": "rectangle",
  "booleanOperation": -1,
  "clippingMaskMode": 0,
  "do_objectID": "AB9F191A-6CBB-4464-9981-A49F46FCDE88",
  "edited": false,
  "exportOptions": {
    "_class": "exportOptions",
    "do_objectID": "7BC2440C-AEAD-4E65-864E-31F1C27CFE04",
    "exportFormats": [
    ],
    "includedLayerIds": [
    ],
    "layerOptions": 0,
    "shouldTrim": false
  },
  "fixedRadius": 0,
  "frame": {
    "_class": "rect",
    "constrainProportions": false,
    "do_objectID": "7A912C5D-EEF7-403C-849A-49239695E03F",
    "height": 83,
    "width": 375,
    "x": 0,
    "y": 0
  },
  "hasClippingMask": false,
  "hasConvertedToNewRoundCorners": true,
  "isClosed": true,
  "isFixedToViewport": false,
  "isFlippedHorizontal": false,
  "isFlippedVertical": false,
  "isLocked": false,
  "isVisible": true,
  "layerListExpandedType": 0,
  "name": "Background",
  "nameIsFixed": true,
  "pointRadiusBehaviour": 0,
  "points": [
    {
      "_class": "curvePoint",
      "cornerRadius": 0,
      "curveFrom": "{0, 0}",
      "curveMode": 1,
      "curveTo": "{0, 0}",
      "hasCurveFrom": false,
      "hasCurveTo": false,
      "point": "{0, 0}"
    },
    {
      "_class": "curvePoint",
      "cornerRadius": 0,
      "curveFrom": "{1.0000000000000009, 0}",
      "curveMode": 1,
      "curveTo": "{1.0000000000000009, 0}",
      "hasCurveFrom": false,
      "hasCurveTo": false,
      "point": "{1.0000000000000009, 0}"
    },
    {
      "_class": "curvePoint",
      "cornerRadius": 0,
      "curveFrom": "{1.0000000000000009, 1}",
      "curveMode": 1,
      "curveTo": "{1.0000000000000009, 1}",
      "hasCurveFrom": false,
      "hasCurveTo": false,
      "point": "{1.0000000000000009, 1}"
    },
    {
      "_class": "curvePoint",
      "cornerRadius": 0,
      "curveFrom": "{0, 1}",
      "curveMode": 1,
      "curveTo": "{0, 1}",
      "hasCurveFrom": false,
      "hasCurveTo": false,
      "point": "{0, 1}"
    }
  ],
  "resizingConstraint": 63,
  "resizingType": 0,
  "rotation": 0,
  "sharedStyleID": "E6E5A31C-DE48-4CD1-85D5-9C3C969F4289",
  "shouldBreakMaskChain": false,
  "style": {
    "_class": "style",
    "blur": {
      "_class": "blur",
      "center": "{0.5, 0.5}",
      "do_objectID": "397B9C3B-4E0F-4336-86AF-5617473A9492",
      "isEnabled": true,
      "motionAngle": 0,
      "radius": 10,
      "saturation": 1,
      "type": 3
    },
    "do_objectID": "F6994361-71DC-421A-9D9D-16134FBE8E4C",
    "endMarkerType": 0,
    "fills": [
      {
        "_class": "fill",
        "color": {
          "_class": "color",
          "alpha": 0.9200000166893005,
          "blue": 0.9725490196078431,
          "green": 0.9725490196078431,
          "red": 0.9725490196078431
        },
        "fillType": 0,
        "isEnabled": true,
        "noiseIndex": 0,
        "noiseIntensity": 0,
        "patternFillType": 0,
        "patternTileScale": 1
      }
    ],
    "miterLimit": 10,
    "startMarkerType": 0,
    "windingRule": 1
  }
}