{
  "_class": "artboard",
  "backgroundColor": {
    "_class": "color",
    "alpha": 1,
    "blue": 1,
    "green": 1,
    "red": 1
  },
  "booleanOperation": -1,
  "clippingMaskMode": 0,
  "do_objectID": "8BE909D3-F4D6-4716-BDF7-DBE757C78415",
  "exportOptions": {
    "_class": "exportOptions",
    "exportFormats": [
      {
        "_class": "exportFormat",
        "absoluteSize": 0,
        "fileFormat": "jpg",
        "name": "",
        "namingScheme": 0,
        "scale": 3,
        "visibleScaleType": 0
      }
    ],
    "includedLayerIds": [
    ],
    "layerOptions": 0,
    "shouldTrim": false
  },
  "frame": {
    "_class": "rect",
    "constrainProportions": false,
    "height": 812,
    "width": 375,
    "x": 1318,
    "y": -401
  },
  "groupLayout": {
    "_class": "MSImmutableFreeformGroupLayout"
  },
  "hasBackgroundColor": false,
  "hasClickThrough": true,
  "hasClippingMask": false,
  "horizontalRulerData": {
    "_class": "rulerData",
    "base": 0,
    "guides": [
    ]
  },
  "includeBackgroundColorInExport": true,
  "includeInCloudUpload": true,
  "isFixedToViewport": false,
  "isFlippedHorizontal": false,
  "isFlippedVertical": false,
  "isFlowHome": false,
  "isLocked": false,
  "isVisible": true,
  "layerListExpandedType": 2,
  "layers": [
    {
      "class": "bitmap",
      "id": "306CAF54-CC26-4452-9341-B05A4712DADA"
    },
    {
      "class": "rectangle",
      "id": "BFE766AA-7625-40B7-90E5-610B6013BD66"
    },
    {
      "class": "rectangle",
      "id": "A53A6367-396C-473B-918D-7C559870D21A"
    },
    {
      "class": "text",
      "id": "423D0CDB-4D0A-49A6-8FF2-75E04B7959DD"
    },
    {
      "class": "text",
      "id": "F63FD055-DE96-46F3-833B-396F761BF533"
    },
    {
      "class": "symbolInstance",
      "id": "FCF0E0FE-D3E5-479C-94F2-6E801BE998C6"
    },
    {
      "class": "symbolInstance",
      "id": "83C8894C-71A8-45C3-955E-2CFC61AB3E7C"
    }
  ],
  "layout": {
    "_class": "layoutGrid",
    "columnWidth": 30,
    "drawHorizontal": false,
    "drawHorizontalLines": false,
    "drawVertical": true,
    "gutterHeight": 12,
    "gutterWidth": 5,
    "guttersOutside": false,
    "horizontalOffset": 15,
    "isEnabled": false,
    "numberOfColumns": 10,
    "rowHeightMultiplication": 5,
    "totalWidth": 345
  },
  "name": "4_Sign Up Copy 2",
  "nameIsFixed": true,
  "presetDictionary": {
    "allowResizedMatching": 1,
    "height": 812,
    "name": "iPhone XS",
    "offersLandscapeVariant": 1,
    "width": 375
  },
  "resizesContent": false,
  "resizingConstraint": 63,
  "resizingType": 0,
  "rotation": 0,
  "shouldBreakMaskChain": true,
  "style": {
    "_class": "style",
    "endMarkerType": 0,
    "miterLimit": 10,
    "startMarkerType": 0,
    "windingRule": 1
  },
  "verticalRulerData": {
    "_class": "rulerData",
    "base": 0,
    "guides": [
    ]
  }
}