{
  "_class": "symbolInstance",
  "booleanOperation": -1,
  "clippingMaskMode": 0,
  "do_objectID": "B5310CA9-AE0E-45A0-AF16-2DFBEFB17B9F",
  "exportOptions": {
    "_class": "exportOptions",
    "do_objectID": "F725FC6F-D8DC-45CD-9B89-E37126B06C8E",
    "exportFormats": [
    ],
    "includedLayerIds": [
    ],
    "layerOptions": 0,
    "shouldTrim": false
  },
  "frame": {
    "_class": "rect",
    "constrainProportions": false,
    "do_objectID": "BFCBE8EA-5EF0-4431-A6E3-F9234121BC49",
    "height": 2,
    "width": 345,
    "x": 30,
    "y": 331
  },
  "hasClippingMask": false,
  "horizontalSpacing": 0,
  "isFixedToViewport": false,
  "isFlippedHorizontal": false,
  "isFlippedVertical": false,
  "isLocked": false,
  "isVisible": true,
  "layerListExpandedType": 0,
  "name": " Divider / 16pt 16pt Copy",
  "nameIsFixed": false,
  "overrideValues": [
  ],
  "resizingConstraint": 63,
  "resizingType": 0,
  "rotation": 0,
  "scale": 1,
  "shouldBreakMaskChain": true,
  "style": {
    "_class": "style",
    "do_objectID": "F27CFA41-B25E-4CCA-B7A5-C5A36F740074",
    "endMarkerType": 0,
    "miterLimit": 10,
    "startMarkerType": 0,
    "windingRule": 1
  },
  "symbolID": "C499128B-FC40-4E36-B12B-30807F650FF2",
  "verticalSpacing": 0
}