{
  "_class": "shapePath",
  "booleanOperation": -1,
  "clippingMaskMode": 0,
  "do_objectID": "C385AC86-4F73-4471-967E-F5021DC53D04",
  "edited": true,
  "exportOptions": {
    "_class": "exportOptions",
    "do_objectID": "C8D895FC-7B9A-4669-838C-458F3F923FC9",
    "exportFormats": [
    ],
    "includedLayerIds": [
    ],
    "layerOptions": 0,
    "shouldTrim": false
  },
  "frame": {
    "_class": "rect",
    "constrainProportions": true,
    "do_objectID": "C826AEC5-CAD4-468C-A4EB-39A6F8D727C0",
    "height": 17.69155324866336,
    "width": 10,
    "x": 350,
    "y": 216
  },
  "hasClippingMask": false,
  "isClosed": true,
  "isFixedToViewport": false,
  "isFlippedHorizontal": false,
  "isFlippedVertical": false,
  "isLocked": false,
  "isVisible": true,
  "layerListExpandedType": 0,
  "name": "Path Copy",
  "nameIsFixed": false,
  "pointRadiusBehaviour": 1,
  "points": [
    {
      "_class": "curvePoint",
      "cornerRadius": 0,
      "curveFrom": "{-0.012855145731757093, 0.90099510056911536}",
      "curveMode": 4,
      "curveTo": "{0.038603918458749706, 0.87160395604444607}",
      "hasCurveFrom": true,
      "hasCurveTo": false,
      "point": "{0.038603918458749706, 0.87160395604444607}"
    },
    {
      "_class": "curvePoint",
      "cornerRadius": 0,
      "curveFrom": "{0.089986063270795336, 1.0073206093488178}",
      "curveMode": 2,
      "curveTo": "{-0.012855145731757093, 0.94858179832392386}",
      "hasCurveFrom": true,
      "hasCurveTo": true,
      "point": "{0.038603918458749706, 0.97797294284859315}"
    },
    {
      "_class": "curvePoint",
      "cornerRadius": 0,
      "curveFrom": "{0.22490265309164567, 0.97797294284859315}",
      "curveMode": 4,
      "curveTo": "{0.1734435889011389, 1.0073640873732623}",
      "hasCurveFrom": false,
      "hasCurveTo": true,
      "point": "{0.22490265309164567, 0.97797294284859315}"
    },
    {
      "_class": "curvePoint",
      "cornerRadius": 0,
      "curveFrom": "{1.0128647660476267, 0.52382323851067425}",
      "curveMode": 4,
      "curveTo": "{0.96140570185711982, 0.55321438303534354}",
      "hasCurveFrom": true,
      "hasCurveTo": false,
      "point": "{0.96140570185711982, 0.55321438303534354}"
    },
    {
      "_class": "curvePoint",
      "cornerRadius": 0,
      "curveFrom": "{0.96140570185711982, 0.44680191820675164}",
      "curveMode": 4,
      "curveTo": "{1.0128647660476267, 0.47619306273142098}",
      "hasCurveFrom": false,
      "hasCurveTo": true,
      "point": "{0.96140570185711982, 0.44680191820675164}"
    },
    {
      "_class": "curvePoint",
      "cornerRadius": 0,
      "curveFrom": "{0.1734435889011389, -0.0073477861311673272}",
      "curveMode": 4,
      "curveTo": "{0.22490265309164562, 0.022043358393501977}",
      "hasCurveFrom": true,
      "hasCurveTo": false,
      "point": "{0.22490265309164562, 0.022043358393501977}"
    },
    {
      "_class": "curvePoint",
      "cornerRadius": 0,
      "curveFrom": "{-0.012855145731757025, 0.051434502918171282}",
      "curveMode": 2,
      "curveTo": "{0.09006298264925644, -0.0073477861311673272}",
      "hasCurveFrom": true,
      "hasCurveTo": true,
      "point": "{0.038603918458749706, 0.022043358393501977}"
    },
    {
      "_class": "curvePoint",
      "cornerRadius": 0,
      "curveFrom": "{0.038526999080288532, 0.1284123451976491}",
      "curveMode": 4,
      "curveTo": "{-0.012855145731757093, 0.099021200672979787}",
      "hasCurveFrom": false,
      "hasCurveTo": true,
      "point": "{0.038526999080288532, 0.1284123451976491}"
    },
    {
      "_class": "curvePoint",
      "cornerRadius": 0,
      "curveFrom": "{0.6425364184464385, 0.49999728111493635}",
      "curveMode": 1,
      "curveTo": "{0.6425364184464385, 0.49999728111493635}",
      "hasCurveFrom": false,
      "hasCurveTo": false,
      "point": "{0.6425364184464385, 0.49999728111493635}"
    }
  ],
  "resizingConstraint": 63,
  "resizingType": 0,
  "rotation": 0,
  "sharedStyleID": "BAAE8FFC-4AE1-41A7-B43D-0B766350B483",
  "shouldBreakMaskChain": false,
  "style": {
    "_class": "style",
    "do_objectID": "13A84F76-4661-4459-97EF-B3B3A31EBD8E",
    "endMarkerType": 0,
    "fills": [
      {
        "_class": "fill",
        "color": {
          "_class": "color",
          "alpha": 1,
          "blue": 0.9176470588235294,
          "green": 0.8980392156862745,
          "red": 0.8980392156862745
        },
        "fillType": 0,
        "isEnabled": true,
        "noiseIndex": 0,
        "noiseIntensity": 0,
        "patternFillType": 1,
        "patternTileScale": 1
      }
    ],
    "miterLimit": 10,
    "startMarkerType": 0,
    "windingRule": 1
  }
}