{
  "_class": "text",
  "attributedString": {
    "_class": "attributedString",
    "attributes": [
      {
        "_class": "stringAttribute",
        "attributes": {
          "MSAttributedStringColorAttribute": {
            "_class": "color",
            "alpha": 1,
            "blue": 1,
            "green": 1,
            "red": 1
          },
          "MSAttributedStringFontAttribute": {
            "_class": "fontDescriptor",
            "attributes": {
              "name": "Avenir-Heavy",
              "size": 11
            }
          },
          "kerning": -0.2652942,
          "paragraphStyle": {
            "_class": "paragraphStyle",
            "alignment": 0,
            "allowsDefaultTighteningForTruncation": 0
          }
        },
        "length": 13,
        "location": 0
      }
    ],
    "string": "Isaiah Martin"
  },
  "automaticallyDrawOnUnderlyingPath": false,
  "booleanOperation": -1,
  "clippingMaskMode": 0,
  "do_objectID": "2664E6F9-7339-430F-AA53-DD9EE742256C",
  "dontSynchroniseWithSymbol": false,
  "exportOptions": {
    "_class": "exportOptions",
    "do_objectID": "77064245-3694-4ED9-9E97-A1E8065E3716",
    "exportFormats": [
    ],
    "includedLayerIds": [
    ],
    "layerOptions": 0,
    "shouldTrim": false
  },
  "frame": {
    "_class": "rect",
    "constrainProportions": false,
    "do_objectID": "AE8271C2-7ED5-4418-AE2B-6751925B9AF8",
    "height": 15,
    "width": 63,
    "x": 44,
    "y": 174
  },
  "glyphBounds": "{{0, 2}, {63, 10}}",
  "hasClippingMask": false,
  "isFixedToViewport": false,
  "isFlippedHorizontal": false,
  "isFlippedVertical": false,
  "isLocked": false,
  "isVisible": true,
  "layerListExpandedType": 0,
  "lineSpacingBehaviour": 2,
  "name": "Isaiah Martin",
  "nameIsFixed": false,
  "resizingConstraint": 47,
  "resizingType": 0,
  "rotation": 0,
  "shouldBreakMaskChain": false,
  "style": {
    "_class": "style",
    "do_objectID": "055B53CC-5FCC-4523-95AA-5854F4B937AC",
    "endMarkerType": 0,
    "miterLimit": 10,
    "startMarkerType": 0,
    "textStyle": {
      "_class": "textStyle",
      "do_objectID": "E100331B-26CF-4B12-931D-A503D1E15288",
      "encodedAttributes": {
        "MSAttributedStringColorAttribute": {
          "_class": "color",
          "alpha": 1,
          "blue": 1,
          "green": 1,
          "red": 1
        },
        "MSAttributedStringFontAttribute": {
          "_class": "fontDescriptor",
          "attributes": {
            "name": "Avenir-Heavy",
            "size": 11
          }
        },
        "kerning": -0.2652942,
        "paragraphStyle": {
          "_class": "paragraphStyle",
          "alignment": 0,
          "allowsDefaultTighteningForTruncation": 0
        }
      },
      "verticalAlignment": 0
    },
    "windingRule": 1
  },
  "textBehaviour": 0,
  "userInfo": {
    "com.invisionlabs.duplicate": {
      "type-duplicate": {
        "action": "name",
        "title": "Both"
      }
    }
  }
}