{
  "_class": "group",
  "booleanOperation": -1,
  "clippingMaskMode": 0,
  "do_objectID": "866E6210-6107-401B-A89D-976D5DDCDB68",
  "exportOptions": {
    "_class": "exportOptions",
    "do_objectID": "E3738AA9-202F-47C0-9BC9-22153A1E44ED",
    "exportFormats": [
    ],
    "includedLayerIds": [
    ],
    "layerOptions": 0,
    "shouldTrim": false
  },
  "frame": {
    "_class": "rect",
    "constrainProportions": false,
    "do_objectID": "F069E3E1-FDB0-4EE4-8342-C1CDDBD37C0D",
    "height": 24,
    "width": 136,
    "x": 8,
    "y": 214
  },
  "groupLayout": {
    "_class": "MSImmutableFreeformGroupLayout"
  },
  "hasClickThrough": false,
  "hasClippingMask": false,
  "isFixedToViewport": false,
  "isFlippedHorizontal": false,
  "isFlippedVertical": false,
  "isLocked": false,
  "isVisible": true,
  "layerListExpandedType": 0,
  "layers": [
    {
      "class": "text",
      "id": "F06035A6-79A4-448B-94F9-3EC5CA2BA2AE"
    },
    {
      "class": "text",
      "id": "4790D228-42D2-4020-BEA6-047B68BD5D1D"
    },
    {
      "class": "symbolInstance",
      "id": "D1597883-994B-4F02-A9A8-280489403E36"
    },
    {
      "class": "symbolInstance",
      "id": "746E9CB4-B5F3-47FC-A9FE-B02E04614B0A"
    }
  ],
  "name": "Group",
  "nameIsFixed": false,
  "resizingConstraint": 63,
  "resizingType": 0,
  "rotation": 0,
  "shouldBreakMaskChain": false,
  "style": {
    "_class": "style",
    "do_objectID": "928373A3-25B2-46E9-A36B-E67ACD0B1BA0",
    "endMarkerType": 0,
    "miterLimit": 10,
    "startMarkerType": 0,
    "windingRule": 1
  }
}